README.md
pyproject.toml
setup.cfg
setup.py
asdf_sextant/DateAxisItem.py
asdf_sextant/__init__.py
asdf_sextant/asdf_sextant_window.py
asdf_sextant/icon.png
asdf_sextant/main.py
asdf_sextant/python_syntax_highlighting.py
asdf_sextant/station_tree_widget.py
asdf_sextant/svg_graphics_view.py
asdf_sextant.egg-info/PKG-INFO
asdf_sextant.egg-info/SOURCES.txt
asdf_sextant.egg-info/dependency_links.txt
asdf_sextant.egg-info/entry_points.txt
asdf_sextant.egg-info/requires.txt
asdf_sextant.egg-info/top_level.txt
asdf_sextant/resources/index.html
asdf_sextant/resources/index_event.html
asdf_sextant/resources/script.js
asdf_sextant/resources/script_event.js