Metadata-Version: 2.1
Name: asdf-sextant
Version: 0.1.2
Summary: GUI to explore ASDF files
Home-page: https://github.com/SeismicData/asdf_sextant
Author: Lion Krischer
Author-email: lion.krischer@gmail.com
License: UNKNOWN
Platform: UNKNOWN
Classifier: Programming Language :: Python :: 3
Requires-Python: >=3.6
